{"undoStack":[{"@type":"Draw","data":{"x":5.0,"y":5.0,"radius":20.0,"strokeWidth":20.0,"id":"s0","fill":"red","stroke":"blue","commandType":"draw","className":"Circle"},"shape":{"@type":"circle","x":5.0,"y":5.0,"scaleX":0.0,"scaleY":0.0,"rotation":0.0,"strokeWidth":20.0,"id":"s0","fill":"red","stroke":"blue","radius":20.0}}],"redoStack":[],"currentShapes":{"s0":{"@type":"circle","x":5.0,"y":5.0,"scaleX":0.0,"scaleY":0.0,"rotation":0.0,"strokeWidth":20.0,"id":"s0","fill":"red","stroke":"blue","radius":20.0}},"idCounter":1}